{"get":"games","parameters":{"date":"2015-09-05"},"errors":[],"results":8,"response":[{"id":315063,"date":"2015-09-05T00:00:00+00:00","time":"00:00","timestamp":1441411200,"timezone":"UTC","stage":null,"week":null,"status":{"long":"Game Finished","short":"FT","timer":null},"league":{"id":13,"name":"NBA W","type":"League","season":2015,"logo":"https:\/\/media-4.api-sports.io\/basketball\/leagues\/13.png"},"country":{"id":5,"name":"USA","code":"US","flag":"https:\/\/media-4.api-sports.io\/flags\/us.svg"},"teams":{"home":{"id":167,"name":"Las Vegas Aces W","logo":"https:\/\/media-4.api-sports.io\/basketball\/teams\/167.png"},"away":{"id":164,"name":"Connecticut Sun W","logo":"https:\/\/media-4.api-sports.io\/basketball\/teams\/164.png"}},"scores":{"home":{"quarter_1":16,"quarter_2":20,"quarter_3":21,"quarter_4":15,"over_time":null,"total":72},"away":{"quarter_1":14,"quarter_2":19,"quarter_3":20,"quarter_4":20,"over_time":null,"total":73}}},{"id":315064,"date":"2015-09-05T00:00:00+00:00","time":"00:00","timestamp":1441411200,"timezone":"UTC","stage":null,"week":null,"status":{"long":"Game Finished","short":"FT","timer":null},"league":{"id":13,"name":"NBA W","type":"League","season":2015,"logo":"https:\/\/media-4.api-sports.io\/basketball\/leagues\/13.png"},"country":{"id":5,"name":"USA","code":"US","flag":"https:\/\/media-4.api-sports.io\/flags\/us.svg"},"teams":{"home":{"id":169,"name":"Minnesota Lynx W","logo":"https:\/\/media-4.api-sports.io\/basketball\/teams\/169.png"},"away":{"id":166,"name":"Indiana Fever W","logo":"https:\/\/media-4.api-sports.io\/basketball\/teams\/166.png"}},"scores":{"home":{"quarter_1":22,"quarter_2":19,"quarter_3":19,"quarter_4":21,"over_time":null,"total":81},"away":{"quarter_1":20,"quarter_2":12,"quarter_3":14,"quarter_4":19,"over_time":null,"total":65}}},{"id":170485,"date":"2015-09-05T01:30:00+00:00","time":"01:30","timestamp":1441416600,"timezone":"UTC","stage":null,"week":null,"status":{"long":"Game Finished","short":"FT","timer":null},"league":{"id":282,"name":"Americas Championship","type":"cup","season":2015,"logo":"https:\/\/media-4.api-sports.io\/basketball\/leagues\/282.png"},"country":{"id":62,"name":"World","code":" ","flag":"https:\/\/media-4.api-sports.io\/flags\/ .svg"},"teams":{"home":{"id":3022,"name":"Mexico","logo":"https:\/\/media-4.api-sports.io\/basketball\/teams\/3022.png"},"away":{"id":3033,"name":"Uruguay","logo":"https:\/\/media-4.api-sports.io\/basketball\/teams\/3033.png"}},"scores":{"home":{"quarter_1":14,"quarter_2":24,"quarter_3":17,"quarter_4":23,"over_time":null,"total":78},"away":{"quarter_1":16,"quarter_2":11,"quarter_3":14,"quarter_4":22,"over_time":null,"total":63}}},{"id":118728,"date":"2015-09-05T08:00:00+00:00","time":"08:00","timestamp":1441440000,"timezone":"UTC","stage":null,"week":"SEABL Women - Semi-finals","status":{"long":"Game Finished","short":"FT","timer":null},"league":{"id":182,"name":"SEABL Women","type":"League","season":2015,"logo":"https:\/\/media-4.api-sports.io\/basketball\/leagues\/182.png"},"country":{"id":1,"name":"Australia","code":"AU","flag":"https:\/\/media-4.api-sports.io\/flags\/au.svg"},"teams":{"home":{"id":70,"name":"Dandenong W","logo":"https:\/\/media-4.api-sports.io\/basketball\/teams\/70.png"},"away":{"id":57,"name":"Geelong W","logo":"https:\/\/media-4.api-sports.io\/basketball\/teams\/57.png"}},"scores":{"home":{"quarter_1":23,"quarter_2":23,"quarter_3":16,"quarter_4":13,"over_time":null,"total":75},"away":{"quarter_1":15,"quarter_2":10,"quarter_3":17,"quarter_4":13,"over_time":null,"total":55}}},{"id":118729,"date":"2015-09-05T09:00:00+00:00","time":"09:00","timestamp":1441443600,"timezone":"UTC","stage":null,"week":"SEABL Women - Semi-finals","status":{"long":"Game Finished","short":"FT","timer":null},"league":{"id":182,"name":"SEABL Women","type":"League","season":2015,"logo":"https:\/\/media-4.api-sports.io\/basketball\/leagues\/182.png"},"country":{"id":1,"name":"Australia","code":"AU","flag":"https:\/\/media-4.api-sports.io\/flags\/au.svg"},"teams":{"home":{"id":32,"name":"Bendigo W","logo":"https:\/\/media-4.api-sports.io\/basketball\/teams\/32.png"},"away":{"id":66,"name":"Kilsyth W","logo":"https:\/\/media-4.api-sports.io\/basketball\/teams\/66.png"}},"scores":{"home":{"quarter_1":18,"quarter_2":21,"quarter_3":15,"quarter_4":23,"over_time":null,"total":77},"away":{"quarter_1":27,"quarter_2":18,"quarter_3":16,"quarter_4":18,"over_time":null,"total":79}}},{"id":118072,"date":"2015-09-05T09:30:00+00:00","time":"09:30","timestamp":1441445400,"timezone":"UTC","stage":null,"week":"SEABL - Semi-finals","status":{"long":"Game Finished","short":"FT","timer":null},"league":{"id":181,"name":"SEABL","type":"League","season":2015,"logo":"https:\/\/media-4.api-sports.io\/basketball\/leagues\/181.png"},"country":{"id":1,"name":"Australia","code":"AU","flag":"https:\/\/media-4.api-sports.io\/flags\/au.svg"},"teams":{"home":{"id":51,"name":"Albury","logo":"https:\/\/media-4.api-sports.io\/basketball\/teams\/51.png"},"away":{"id":38,"name":"Geelong","logo":"https:\/\/media-4.api-sports.io\/basketball\/teams\/38.png"}},"scores":{"home":{"quarter_1":20,"quarter_2":23,"quarter_3":20,"quarter_4":21,"over_time":null,"total":84},"away":{"quarter_1":14,"quarter_2":19,"quarter_3":16,"quarter_4":29,"over_time":null,"total":78}}},{"id":173452,"date":"2015-09-05T09:30:00+00:00","time":"09:30","timestamp":1441445400,"timezone":"UTC","stage":null,"week":"Asia Cup Women - 3rd place","status":{"long":"Game Finished","short":"FT","timer":null},"league":{"id":310,"name":"Asia Cup Women","type":"cup","season":2015,"logo":"https:\/\/media-4.api-sports.io\/basketball\/leagues\/310.png"},"country":{"id":2,"name":"Asia","code":null,"flag":null},"teams":{"home":{"id":4355,"name":"Chinese T. W","logo":"https:\/\/media-4.api-sports.io\/basketball\/teams\/4355.png"},"away":{"id":3047,"name":"South Korea W","logo":"https:\/\/media-4.api-sports.io\/basketball\/teams\/3047.png"}},"scores":{"home":{"quarter_1":6,"quarter_2":15,"quarter_3":15,"quarter_4":9,"over_time":null,"total":45},"away":{"quarter_1":13,"quarter_2":14,"quarter_3":19,"quarter_4":6,"over_time":null,"total":52}}},{"id":173453,"date":"2015-09-05T11:30:00+00:00","time":"11:30","timestamp":1441452600,"timezone":"UTC","stage":null,"week":"Asia Cup Women - Final","status":{"long":"Game Finished","short":"FT","timer":null},"league":{"id":310,"name":"Asia Cup Women","type":"cup","season":2015,"logo":"https:\/\/media-4.api-sports.io\/basketball\/leagues\/310.png"},"country":{"id":2,"name":"Asia","code":null,"flag":null},"teams":{"home":{"id":3042,"name":"Japan W","logo":"https:\/\/media-4.api-sports.io\/basketball\/teams\/3042.png"},"away":{"id":3039,"name":"China W","logo":"https:\/\/media-4.api-sports.io\/basketball\/teams\/3039.png"}},"scores":{"home":{"quarter_1":23,"quarter_2":21,"quarter_3":24,"quarter_4":17,"over_time":null,"total":85},"away":{"quarter_1":11,"quarter_2":11,"quarter_3":12,"quarter_4":16,"over_time":null,"total":50}}}]}