{"get":"games","parameters":{"date":"2015-01-12"},"errors":[],"results":25,"response":[{"id":197935,"date":"2015-01-12T00:30:00+00:00","time":"00:30","timestamp":1421022600,"timezone":"UTC","stage":null,"week":null,"status":{"long":"Game Finished","short":"FT","timer":null},"league":{"id":18,"name":"Liga A","type":"League","season":"2014-2015","logo":"https:\/\/media-4.api-sports.io\/basketball\/leagues\/18.png"},"country":{"id":6,"name":"Argentina","code":"AR","flag":"https:\/\/media-4.api-sports.io\/flags\/ar.svg"},"teams":{"home":{"id":296,"name":"Regatas","logo":"https:\/\/media-4.api-sports.io\/basketball\/teams\/296.png"},"away":{"id":1398,"name":"Quilmes","logo":"https:\/\/media-4.api-sports.io\/basketball\/teams\/1398.png"}},"scores":{"home":{"quarter_1":15,"quarter_2":18,"quarter_3":21,"quarter_4":18,"over_time":null,"total":72},"away":{"quarter_1":15,"quarter_2":22,"quarter_3":27,"quarter_4":15,"over_time":null,"total":79}}},{"id":197936,"date":"2015-01-12T00:30:00+00:00","time":"00:30","timestamp":1421022600,"timezone":"UTC","stage":null,"week":null,"status":{"long":"Game Finished","short":"FT","timer":null},"league":{"id":18,"name":"Liga A","type":"League","season":"2014-2015","logo":"https:\/\/media-4.api-sports.io\/basketball\/leagues\/18.png"},"country":{"id":6,"name":"Argentina","code":"AR","flag":"https:\/\/media-4.api-sports.io\/flags\/ar.svg"},"teams":{"home":{"id":284,"name":"Estudiantes","logo":"https:\/\/media-4.api-sports.io\/basketball\/teams\/284.png"},"away":{"id":5050,"name":"Sionista","logo":"https:\/\/media-4.api-sports.io\/basketball\/teams\/5050.png"}},"scores":{"home":{"quarter_1":20,"quarter_2":10,"quarter_3":21,"quarter_4":20,"over_time":null,"total":71},"away":{"quarter_1":11,"quarter_2":16,"quarter_3":14,"quarter_4":24,"over_time":null,"total":65}}},{"id":197937,"date":"2015-01-12T00:30:00+00:00","time":"00:30","timestamp":1421022600,"timezone":"UTC","stage":null,"week":null,"status":{"long":"Game Finished","short":"FT","timer":null},"league":{"id":18,"name":"Liga A","type":"League","season":"2014-2015","logo":"https:\/\/media-4.api-sports.io\/basketball\/leagues\/18.png"},"country":{"id":6,"name":"Argentina","code":"AR","flag":"https:\/\/media-4.api-sports.io\/flags\/ar.svg"},"teams":{"home":{"id":280,"name":"Argentino","logo":"https:\/\/media-4.api-sports.io\/basketball\/teams\/280.png"},"away":{"id":282,"name":"Boca Juniors","logo":"https:\/\/media-4.api-sports.io\/basketball\/teams\/282.png"}},"scores":{"home":{"quarter_1":26,"quarter_2":19,"quarter_3":19,"quarter_4":12,"over_time":null,"total":76},"away":{"quarter_1":16,"quarter_2":12,"quarter_3":18,"quarter_4":23,"over_time":null,"total":69}}},{"id":303886,"date":"2015-01-12T02:00:00+00:00","time":"02:00","timestamp":1421028000,"timezone":"UTC","stage":null,"week":null,"status":{"long":"Game Finished","short":"FT","timer":null},"league":{"id":12,"name":"NBA","type":"League","season":"2014-2015","logo":"https:\/\/media-4.api-sports.io\/basketball\/leagues\/12.png"},"country":{"id":5,"name":"USA","code":"US","flag":"https:\/\/media-4.api-sports.io\/flags\/us.svg"},"teams":{"home":{"id":157,"name":"Sacramento Kings","logo":"https:\/\/media-4.api-sports.io\/basketball\/teams\/157.png"},"away":{"id":137,"name":"Cleveland Cavaliers","logo":"https:\/\/media-4.api-sports.io\/basketball\/teams\/137.png"}},"scores":{"home":{"quarter_1":30,"quarter_2":29,"quarter_3":26,"quarter_4":18,"over_time":null,"total":103},"away":{"quarter_1":29,"quarter_2":15,"quarter_3":20,"quarter_4":20,"over_time":null,"total":84}}},{"id":303887,"date":"2015-01-12T02:30:00+00:00","time":"02:30","timestamp":1421029800,"timezone":"UTC","stage":null,"week":null,"status":{"long":"Game Finished","short":"FT","timer":null},"league":{"id":12,"name":"NBA","type":"League","season":"2014-2015","logo":"https:\/\/media-4.api-sports.io\/basketball\/leagues\/12.png"},"country":{"id":5,"name":"USA","code":"US","flag":"https:\/\/media-4.api-sports.io\/flags\/us.svg"},"teams":{"home":{"id":145,"name":"Los Angeles Lakers","logo":"https:\/\/media-4.api-sports.io\/basketball\/teams\/145.png"},"away":{"id":156,"name":"Portland Trail Blazers","logo":"https:\/\/media-4.api-sports.io\/basketball\/teams\/156.png"}},"scores":{"home":{"quarter_1":20,"quarter_2":25,"quarter_3":24,"quarter_4":25,"over_time":null,"total":94},"away":{"quarter_1":23,"quarter_2":27,"quarter_3":22,"quarter_4":34,"over_time":null,"total":106}}},{"id":286054,"date":"2015-01-12T10:00:00+00:00","time":"10:00","timestamp":1421056800,"timezone":"UTC","stage":null,"week":null,"status":{"long":"Game Finished","short":"FT","timer":null},"league":{"id":92,"name":"WKBL W","type":"League","season":"2014-2015","logo":"https:\/\/media-4.api-sports.io\/basketball\/leagues\/92.png"},"country":{"id":44,"name":"South Korea","code":"KR","flag":"https:\/\/media-4.api-sports.io\/flags\/kr.svg"},"teams":{"home":{"id":1113,"name":"KB Stars W","logo":"https:\/\/media-4.api-sports.io\/basketball\/teams\/1113.png"},"away":{"id":1117,"name":"Woori Wibee W","logo":"https:\/\/media-4.api-sports.io\/basketball\/teams\/1117.png"}},"scores":{"home":{"quarter_1":11,"quarter_2":12,"quarter_3":17,"quarter_4":31,"over_time":null,"total":71},"away":{"quarter_1":18,"quarter_2":9,"quarter_3":14,"quarter_4":14,"over_time":null,"total":55}}},{"id":249048,"date":"2015-01-12T16:00:00+00:00","time":"16:00","timestamp":1421078400,"timezone":"UTC","stage":null,"week":"12","status":{"long":"Game Finished","short":"FT","timer":null},"league":{"id":45,"name":"Basket League","type":"League","season":"2014-2015","logo":"https:\/\/media-4.api-sports.io\/basketball\/leagues\/45.png"},"country":{"id":18,"name":"Greece","code":"GR","flag":"https:\/\/media-4.api-sports.io\/flags\/gr.svg"},"teams":{"home":{"id":1542,"name":"Olympiakos","logo":"https:\/\/media-4.api-sports.io\/basketball\/teams\/1542.png"},"away":{"id":606,"name":"Aris","logo":"https:\/\/media-4.api-sports.io\/basketball\/teams\/606.png"}},"scores":{"home":{"quarter_1":17,"quarter_2":28,"quarter_3":22,"quarter_4":17,"over_time":null,"total":84},"away":{"quarter_1":17,"quarter_2":18,"quarter_3":14,"quarter_4":19,"over_time":null,"total":68}}},{"id":263622,"date":"2015-01-12T16:30:00+00:00","time":"16:30","timestamp":1421080200,"timezone":"UTC","stage":null,"week":null,"status":{"long":"Game Finished","short":"FT","timer":null},"league":{"id":60,"name":"LKL","type":"League","season":"2014-2015","logo":"https:\/\/media-4.api-sports.io\/basketball\/leagues\/60.png"},"country":{"id":27,"name":"Lithuania","code":"LT","flag":"https:\/\/media-4.api-sports.io\/flags\/lt.svg"},"teams":{"home":{"id":796,"name":"Zalgiris Kaunas","logo":"https:\/\/media-4.api-sports.io\/basketball\/teams\/796.png"},"away":{"id":794,"name":"Rytas","logo":"https:\/\/media-4.api-sports.io\/basketball\/teams\/794.png"}},"scores":{"home":{"quarter_1":23,"quarter_2":21,"quarter_3":23,"quarter_4":24,"over_time":null,"total":91},"away":{"quarter_1":20,"quarter_2":18,"quarter_3":23,"quarter_4":16,"over_time":null,"total":77}}},{"id":211082,"date":"2015-01-12T17:00:00+00:00","time":"17:00","timestamp":1421082000,"timezone":"UTC","stage":null,"week":"27","status":{"long":"Game Finished","short":"FT","timer":null},"league":{"id":32,"name":"NBL","type":"League","season":"2014-2015","logo":"https:\/\/media-4.api-sports.io\/basketball\/leagues\/32.png"},"country":{"id":12,"name":"Czech Republic","code":"CZ","flag":"https:\/\/media-4.api-sports.io\/flags\/cz.svg"},"teams":{"home":{"id":450,"name":"Svitavy","logo":"https:\/\/media-4.api-sports.io\/basketball\/teams\/450.png"},"away":{"id":445,"name":"NH Ostrava","logo":"https:\/\/media-4.api-sports.io\/basketball\/teams\/445.png"}},"scores":{"home":{"quarter_1":17,"quarter_2":21,"quarter_3":18,"quarter_4":20,"over_time":null,"total":76},"away":{"quarter_1":12,"quarter_2":18,"quarter_3":22,"quarter_4":17,"over_time":null,"total":69}}},{"id":249049,"date":"2015-01-12T17:00:00+00:00","time":"17:00","timestamp":1421082000,"timezone":"UTC","stage":null,"week":"12","status":{"long":"Game Finished","short":"FT","timer":null},"league":{"id":45,"name":"Basket League","type":"League","season":"2014-2015","logo":"https:\/\/media-4.api-sports.io\/basketball\/leagues\/45.png"},"country":{"id":18,"name":"Greece","code":"GR","flag":"https:\/\/media-4.api-sports.io\/flags\/gr.svg"},"teams":{"home":{"id":614,"name":"Panathinaikos","logo":"https:\/\/media-4.api-sports.io\/basketball\/teams\/614.png"},"away":{"id":5266,"name":"Panelefsiniakos","logo":"https:\/\/media-4.api-sports.io\/basketball\/teams\/5266.png"}},"scores":{"home":{"quarter_1":15,"quarter_2":25,"quarter_3":27,"quarter_4":24,"over_time":null,"total":91},"away":{"quarter_1":16,"quarter_2":10,"quarter_3":16,"quarter_4":12,"over_time":null,"total":54}}},{"id":277873,"date":"2015-01-12T17:00:00+00:00","time":"17:00","timestamp":1421082000,"timezone":"UTC","stage":null,"week":"15","status":{"long":"Game Finished","short":"FT","timer":null},"league":{"id":82,"name":"VTB United League","type":"League","season":"2014-2015","logo":"https:\/\/media-4.api-sports.io\/basketball\/leagues\/82.png"},"country":{"id":39,"name":"Russia","code":"RU","flag":"https:\/\/media-4.api-sports.io\/flags\/ru.svg"},"teams":{"home":{"id":1026,"name":"Nizhny Novgorod","logo":"https:\/\/media-4.api-sports.io\/basketball\/teams\/1026.png"},"away":{"id":446,"name":"Nymburk","logo":"https:\/\/media-4.api-sports.io\/basketball\/teams\/446.png"}},"scores":{"home":{"quarter_1":18,"quarter_2":24,"quarter_3":22,"quarter_4":25,"over_time":null,"total":89},"away":{"quarter_1":21,"quarter_2":15,"quarter_3":19,"quarter_4":25,"over_time":null,"total":80}}},{"id":257051,"date":"2015-01-12T17:40:00+00:00","time":"17:40","timestamp":1421084400,"timezone":"UTC","stage":null,"week":"15","status":{"long":"Game Finished","short":"FT","timer":null},"league":{"id":51,"name":"Super League","type":"League","season":"2014-2015","logo":"https:\/\/media-4.api-sports.io\/basketball\/leagues\/51.png"},"country":{"id":22,"name":"Israel","code":"IL","flag":"https:\/\/media-4.api-sports.io\/flags\/il.svg"},"teams":{"home":{"id":679,"name":"Hapoel Eilat","logo":"https:\/\/media-4.api-sports.io\/basketball\/teams\/679.png"},"away":{"id":1566,"name":"Bnei Herzliya","logo":"https:\/\/media-4.api-sports.io\/basketball\/teams\/1566.png"}},"scores":{"home":{"quarter_1":26,"quarter_2":24,"quarter_3":21,"quarter_4":23,"over_time":null,"total":94},"away":{"quarter_1":26,"quarter_2":22,"quarter_3":25,"quarter_4":31,"over_time":null,"total":104}}},{"id":257052,"date":"2015-01-12T17:50:00+00:00","time":"17:50","timestamp":1421085000,"timezone":"UTC","stage":null,"week":"15","status":{"long":"After Over Time","short":"AOT","timer":null},"league":{"id":51,"name":"Super League","type":"League","season":"2014-2015","logo":"https:\/\/media-4.api-sports.io\/basketball\/leagues\/51.png"},"country":{"id":22,"name":"Israel","code":"IL","flag":"https:\/\/media-4.api-sports.io\/flags\/il.svg"},"teams":{"home":{"id":680,"name":"Hapoel Holon","logo":"https:\/\/media-4.api-sports.io\/basketball\/teams\/680.png"},"away":{"id":684,"name":"Maccabi Ashdod","logo":"https:\/\/media-4.api-sports.io\/basketball\/teams\/684.png"}},"scores":{"home":{"quarter_1":23,"quarter_2":17,"quarter_3":22,"quarter_4":11,"over_time":10,"total":83},"away":{"quarter_1":19,"quarter_2":22,"quarter_3":22,"quarter_4":10,"over_time":8,"total":81}}},{"id":215004,"date":"2015-01-12T18:00:00+00:00","time":"18:00","timestamp":1421085600,"timezone":"UTC","stage":null,"week":"16","status":{"long":"Game Finished","short":"FT","timer":null},"league":{"id":34,"name":"Basketligaen","type":"League","season":"2014-2015","logo":"https:\/\/media-4.api-sports.io\/basketball\/leagues\/34.png"},"country":{"id":13,"name":"Denmark","code":"DK","flag":"https:\/\/media-4.api-sports.io\/flags\/dk.svg"},"teams":{"home":{"id":2663,"name":"Sisu","logo":"https:\/\/media-4.api-sports.io\/basketball\/teams\/2663.png"},"away":{"id":468,"name":"Horsens","logo":"https:\/\/media-4.api-sports.io\/basketball\/teams\/468.png"}},"scores":{"home":{"quarter_1":13,"quarter_2":19,"quarter_3":20,"quarter_4":16,"over_time":null,"total":68},"away":{"quarter_1":20,"quarter_2":21,"quarter_3":18,"quarter_4":29,"over_time":null,"total":88}}},{"id":215005,"date":"2015-01-12T18:00:00+00:00","time":"18:00","timestamp":1421085600,"timezone":"UTC","stage":null,"week":"16","status":{"long":"Game Finished","short":"FT","timer":null},"league":{"id":34,"name":"Basketligaen","type":"League","season":"2014-2015","logo":"https:\/\/media-4.api-sports.io\/basketball\/leagues\/34.png"},"country":{"id":13,"name":"Denmark","code":"DK","flag":"https:\/\/media-4.api-sports.io\/flags\/dk.svg"},"teams":{"home":{"id":469,"name":"Randers","logo":"https:\/\/media-4.api-sports.io\/basketball\/teams\/469.png"},"away":{"id":472,"name":"Vaerlose","logo":"https:\/\/media-4.api-sports.io\/basketball\/teams\/472.png"}},"scores":{"home":{"quarter_1":21,"quarter_2":28,"quarter_3":16,"quarter_4":11,"over_time":null,"total":76},"away":{"quarter_1":27,"quarter_2":16,"quarter_3":31,"quarter_4":17,"over_time":null,"total":91}}},{"id":257053,"date":"2015-01-12T18:00:00+00:00","time":"18:00","timestamp":1421085600,"timezone":"UTC","stage":null,"week":"15","status":{"long":"Game Finished","short":"FT","timer":null},"league":{"id":51,"name":"Super League","type":"League","season":"2014-2015","logo":"https:\/\/media-4.api-sports.io\/basketball\/leagues\/51.png"},"country":{"id":22,"name":"Israel","code":"IL","flag":"https:\/\/media-4.api-sports.io\/flags\/il.svg"},"teams":{"home":{"id":688,"name":"Nes Ziona","logo":"https:\/\/media-4.api-sports.io\/basketball\/teams\/688.png"},"away":{"id":686,"name":"Maccabi Rishon","logo":"https:\/\/media-4.api-sports.io\/basketball\/teams\/686.png"}},"scores":{"home":{"quarter_1":23,"quarter_2":31,"quarter_3":26,"quarter_4":23,"over_time":null,"total":103},"away":{"quarter_1":24,"quarter_2":17,"quarter_3":13,"quarter_4":26,"over_time":null,"total":80}}},{"id":215006,"date":"2015-01-12T18:15:00+00:00","time":"18:15","timestamp":1421086500,"timezone":"UTC","stage":null,"week":"11","status":{"long":"Game Finished","short":"FT","timer":null},"league":{"id":34,"name":"Basketligaen","type":"League","season":"2014-2015","logo":"https:\/\/media-4.api-sports.io\/basketball\/leagues\/34.png"},"country":{"id":13,"name":"Denmark","code":"DK","flag":"https:\/\/media-4.api-sports.io\/flags\/dk.svg"},"teams":{"home":{"id":470,"name":"Svendborg","logo":"https:\/\/media-4.api-sports.io\/basketball\/teams\/470.png"},"away":{"id":464,"name":"Bakken Bears","logo":"https:\/\/media-4.api-sports.io\/basketball\/teams\/464.png"}},"scores":{"home":{"quarter_1":20,"quarter_2":28,"quarter_3":21,"quarter_4":24,"over_time":null,"total":93},"away":{"quarter_1":29,"quarter_2":24,"quarter_3":24,"quarter_4":18,"over_time":null,"total":95}}},{"id":216815,"date":"2015-01-12T18:30:00+00:00","time":"18:30","timestamp":1421087400,"timezone":"UTC","stage":null,"week":null,"status":{"long":"Game Finished","short":"FT","timer":null},"league":{"id":36,"name":"Korvpalli Meistriliiga","type":"League","season":"2014-2015","logo":"https:\/\/media-4.api-sports.io\/basketball\/leagues\/36.png"},"country":{"id":14,"name":"Estonia","code":"EE","flag":"https:\/\/media-4.api-sports.io\/flags\/ee.svg"},"teams":{"home":{"id":1468,"name":"Audentese","logo":"https:\/\/media-4.api-sports.io\/basketball\/teams\/1468.png"},"away":{"id":480,"name":"BC Kalev\/Cramo","logo":"https:\/\/media-4.api-sports.io\/basketball\/teams\/480.png"}},"scores":{"home":{"quarter_1":7,"quarter_2":14,"quarter_3":12,"quarter_4":13,"over_time":null,"total":46},"away":{"quarter_1":26,"quarter_2":29,"quarter_3":23,"quarter_4":24,"over_time":null,"total":102}}},{"id":257054,"date":"2015-01-12T18:50:00+00:00","time":"18:50","timestamp":1421088600,"timezone":"UTC","stage":null,"week":"15","status":{"long":"Game Finished","short":"FT","timer":null},"league":{"id":51,"name":"Super League","type":"League","season":"2014-2015","logo":"https:\/\/media-4.api-sports.io\/basketball\/leagues\/51.png"},"country":{"id":22,"name":"Israel","code":"IL","flag":"https:\/\/media-4.api-sports.io\/flags\/il.svg"},"teams":{"home":{"id":683,"name":"Ironi Nahariya","logo":"https:\/\/media-4.api-sports.io\/basketball\/teams\/683.png"},"away":{"id":687,"name":"Maccabi Tel Aviv","logo":"https:\/\/media-4.api-sports.io\/basketball\/teams\/687.png"}},"scores":{"home":{"quarter_1":20,"quarter_2":15,"quarter_3":19,"quarter_4":22,"over_time":null,"total":76},"away":{"quarter_1":27,"quarter_2":25,"quarter_3":30,"quarter_4":21,"over_time":null,"total":103}}},{"id":258805,"date":"2015-01-12T19:00:00+00:00","time":"19:00","timestamp":1421089200,"timezone":"UTC","stage":null,"week":"15","status":{"long":"Game Finished","short":"FT","timer":null},"league":{"id":52,"name":"Lega A","type":"League","season":"2014-2015","logo":"https:\/\/media-4.api-sports.io\/basketball\/leagues\/52.png"},"country":{"id":23,"name":"Italy","code":"IT","flag":"https:\/\/media-4.api-sports.io\/flags\/it.svg"},"teams":{"home":{"id":724,"name":"Pistoia","logo":"https:\/\/media-4.api-sports.io\/basketball\/teams\/724.png"},"away":{"id":722,"name":"Olimpia Milano","logo":"https:\/\/media-4.api-sports.io\/basketball\/teams\/722.png"}},"scores":{"home":{"quarter_1":23,"quarter_2":20,"quarter_3":14,"quarter_4":16,"over_time":null,"total":73},"away":{"quarter_1":25,"quarter_2":15,"quarter_3":17,"quarter_4":22,"over_time":null,"total":79}}},{"id":250613,"date":"2015-01-12T19:15:00+00:00","time":"19:15","timestamp":1421090100,"timezone":"UTC","stage":null,"week":null,"status":{"long":"Game Finished","short":"FT","timer":null},"league":{"id":48,"name":"Premier league","type":"League","season":"2014-2015","logo":"https:\/\/media-4.api-sports.io\/basketball\/leagues\/48.png"},"country":{"id":20,"name":"Iceland","code":"IS","flag":"https:\/\/media-4.api-sports.io\/flags\/is.svg"},"teams":{"home":{"id":648,"name":"IR","logo":"https:\/\/media-4.api-sports.io\/basketball\/teams\/648.png"},"away":{"id":654,"name":"Thorl","logo":"https:\/\/media-4.api-sports.io\/basketball\/teams\/654.png"}},"scores":{"home":{"quarter_1":28,"quarter_2":21,"quarter_3":29,"quarter_4":23,"over_time":null,"total":101},"away":{"quarter_1":30,"quarter_2":31,"quarter_3":26,"quarter_4":27,"over_time":null,"total":114}}},{"id":206566,"date":"2015-01-12T19:30:00+00:00","time":"19:30","timestamp":1421091000,"timezone":"UTC","stage":null,"week":null,"status":{"long":"Game Finished","short":"FT","timer":null},"league":{"id":29,"name":"CIS","type":"League","season":"2014-2015","logo":"https:\/\/media-4.api-sports.io\/basketball\/leagues\/29.png"},"country":{"id":9,"name":"Canada","code":"CA","flag":"https:\/\/media-4.api-sports.io\/flags\/ca.svg"},"teams":{"home":{"id":383,"name":"Memorial","logo":"https:\/\/media-4.api-sports.io\/basketball\/teams\/383.png"},"away":{"id":369,"name":"Cape Breton","logo":"https:\/\/media-4.api-sports.io\/basketball\/teams\/369.png"}},"scores":{"home":{"quarter_1":11,"quarter_2":21,"quarter_3":24,"quarter_4":27,"over_time":null,"total":83},"away":{"quarter_1":16,"quarter_2":17,"quarter_3":14,"quarter_4":15,"over_time":null,"total":62}}},{"id":218466,"date":"2015-01-12T19:30:00+00:00","time":"19:30","timestamp":1421091000,"timezone":"UTC","stage":null,"week":"17","status":{"long":"Game Finished","short":"FT","timer":null},"league":{"id":198,"name":"ABA League","type":"cup","season":2014,"logo":"https:\/\/media-4.api-sports.io\/basketball\/leagues\/198.png"},"country":{"id":55,"name":"Europe","code":" ","flag":"https:\/\/media-4.api-sports.io\/flags\/ .svg"},"teams":{"home":{"id":420,"name":"Zadar","logo":"https:\/\/media-4.api-sports.io\/basketball\/teams\/420.png"},"away":{"id":410,"name":"Cibona","logo":"https:\/\/media-4.api-sports.io\/basketball\/teams\/410.png"}},"scores":{"home":{"quarter_1":15,"quarter_2":23,"quarter_3":22,"quarter_4":17,"over_time":null,"total":77},"away":{"quarter_1":10,"quarter_2":10,"quarter_3":13,"quarter_4":18,"over_time":null,"total":51}}},{"id":28857,"date":"2015-01-12T22:00:00+00:00","time":"22:00","timestamp":1421100000,"timezone":"UTC","stage":null,"week":null,"status":{"long":"Game Finished","short":"FT","timer":null},"league":{"id":27,"name":"LBF W","type":"League","season":"2014-2015","logo":"https:\/\/media-4.api-sports.io\/basketball\/leagues\/27.png"},"country":{"id":8,"name":"Brazil","code":"BR","flag":"https:\/\/media-4.api-sports.io\/flags\/br.svg"},"teams":{"home":{"id":1435,"name":"Sicredi W","logo":"https:\/\/media-4.api-sports.io\/basketball\/teams\/1435.png"},"away":{"id":1430,"name":"Barretos W","logo":"https:\/\/media-4.api-sports.io\/basketball\/teams\/1430.png"}},"scores":{"home":{"quarter_1":14,"quarter_2":9,"quarter_3":14,"quarter_4":17,"over_time":null,"total":54},"away":{"quarter_1":11,"quarter_2":9,"quarter_3":16,"quarter_4":24,"over_time":null,"total":60}}},{"id":202966,"date":"2015-01-12T22:00:00+00:00","time":"22:00","timestamp":1421100000,"timezone":"UTC","stage":null,"week":"4","status":{"long":"Game Finished","short":"FT","timer":null},"league":{"id":26,"name":"NBB","type":"League","season":"2014-2015","logo":"https:\/\/media-4.api-sports.io\/basketball\/leagues\/26.png"},"country":{"id":8,"name":"Brazil","code":"BR","flag":"https:\/\/media-4.api-sports.io\/flags\/br.svg"},"teams":{"home":{"id":331,"name":"Cearense","logo":"https:\/\/media-4.api-sports.io\/basketball\/teams\/331.png"},"away":{"id":5100,"name":"Unitri Universo","logo":"https:\/\/media-4.api-sports.io\/basketball\/teams\/5100.png"}},"scores":{"home":{"quarter_1":17,"quarter_2":17,"quarter_3":32,"quarter_4":14,"over_time":null,"total":80},"away":{"quarter_1":15,"quarter_2":13,"quarter_3":12,"quarter_4":22,"over_time":null,"total":62}}}]}